{"swagger":"2.0","info":{"version":"","title":"[CalAccrual][DLoan][Interest]_Open_Account_20190812","description":null},"host":"","basePath":"","paths":{"{{url-smith-dloan-kafka-api}}/raw_msg/{{host-smith-dloan-kafka}}/open-account":{"post":{"tags":[],"summary":null,"operationId":"[CalAccrual][DLoan][Set-1]_Open_Account_TC_Interest_calAccrual_ManualRepay_01_","produces":["application/json"],"consumes":["application/json"],"parameters":[{"name":"x-request-id","in":"header","description":"","required":true,"type":"string"},{"name":"x-job-id","in":"header","description":"","required":true,"type":"string"},{"name":"x-real-ip","in":"header","description":"","required":true,"type":"string"},{"name":"x-caller-service","in":"header","description":"","required":true,"type":"string"},{"name":"x-caller-domain","in":"header","description":"","required":true,"type":"string"},{"name":"datetime","in":"header","description":"","required":true,"type":"string"},{"name":"accept","in":"header","description":"","required":true,"type":"string"},{"name":"accept-language","in":"header","description":"","required":true,"type":"string"},{"name":"accept-encoding","in":"header","description":"","required":true,"type":"string"},{"name":"Content-Type","in":"header","description":"","required":true,"type":"string"},{"name":"x-device","in":"header","description":"","required":true,"type":"string"},{"name":"user-agent","in":"header","description":"","required":true,"type":"string"},{"name":"client_id","in":"header","description":"","required":true,"type":"string"},{"name":"secret","in":"header","description":"","required":true,"type":"string"},{"name":"x-application","in":"header","description":"","required":true,"type":"string"},{"name":"x-channel","in":"header","description":"","required":true,"type":"string"},{"name":"user-agent","in":"header","description":"","required":true,"type":"string"},{"name":"Fnx-Header","in":"header","description":"","required":true,"type":"string"},{"in":"body","name":"body","description":"","required":true,"schema":{"type":"object","properties":{"rq_header":{"type":"object","properties":{"message-id":{"type":"string","example":"{{message-id}}"},"x-job-id":{"type":"string","example":"{{message-id}}"},"x-real-ip":{"type":"string","example":"127.0.0.1"},"x-caller-service":{"type":"string","example":"FrontEnd"},"x-caller-domain":{"type":"string","example":"Front"},"datetime":{"type":"string","example":"{{datetime}}"},"requested-service":{"type":"string","example":"/dloan-account/opened-account-journal"},"requested-service-version":{"type":"string","example":"v1"},"accept":{"type":"string","example":"application/json"},"accept-language":{"type":"string","example":""},"accept-encoding":{"type":"string","example":""},"Content-Type":{"type":"string","example":"application/json"},"x-device":{"type":"string","example":""},"user-agent":{"type":"string","example":""},"client_id":{"type":"string","example":"{{API_ClientId}}"},"secret":{"type":"string","example":"{{API_ClientSecret}}"},"x-application":{"type":"string","example":""},"x-channel":{"type":"string","example":""},"Fnx-Header":{"type":"string","example":"{'identity':{'userRoles':['developer']}}"}},"required":["message-id","x-job-id","x-real-ip","x-caller-service","x-caller-domain","datetime","requested-service","requested-service-version","accept","accept-language","accept-encoding","Content-Type","x-device","user-agent","client_id","secret","x-application","x-channel","Fnx-Header"]},"rq_body":{"type":"object","properties":{"customer_number":{"type":"string","example":"111111111101"},"customer_type":{"type":"string","example":"0702"},"account_number":{"type":"string","example":"{{account}}"},"account_name":{"type":"string","example":"จินตนา การดี"},"account_name_2":{"type":"string","example":"Jintana Karndee"},"credit_limit":{"type":"number","example":400000},"credit_term_number":{"type":"number","example":10},"credit_term_unit":{"type":"string","example":"M"},"product_name":{"type":"string","example":"8100410010417"},"disbursement_account":{"type":"string","example":"20000002011"},"deduction_account":{"type":"string","example":"20000025911"},"account_branch":{"type":"number","example":1},"application_id":{"type":"string","example":"APP0001"},"open_date":{"type":"string","example":"{{open_date}}"},"maturity_date":{"type":"string","example":"{{maturity_date}}"},"special_project_code":{"type":"string","example":"project01"},"finality_code":{"type":"string","example":"finalty01"},"external_product_code":{"type":"string","example":"111111111"},"payment":{"type":"object","properties":{"payment_frequency":{"type":"number","example":1},"payment_unit":{"type":"string","example":"M"},"payment_date":{"type":"number","example":9},"billing_offset_day":{"type":"number","example":1}},"required":["payment_frequency","payment_unit","payment_date","billing_offset_day"]},"interest":{"type":"object","properties":{"interest_index":{"type":"string","example":"MRR"},"interest_spread":{"type":"number","example":13.88}},"required":["interest_index","interest_spread"]},"plan":{"type":"object","properties":{"interest_plan_name":{"type":"string","example":"intlazada"},"penalty_plan_name":{"type":"string","example":"penalty03"},"transaction_plan_name":{"type":"string","example":"txnlazada"},"payment_plan_name":{"type":"string","example":"pmtlazada"},"grace_plan_name":{"type":"string","example":"gracelazada2"}},"required":["interest_plan_name","penalty_plan_name","transaction_plan_name","payment_plan_name","grace_plan_name"]}},"required":["customer_number","customer_type","account_number","account_name","account_name_2","credit_limit","credit_term_number","credit_term_unit","product_name","disbursement_account","deduction_account","account_branch","application_id","open_date","maturity_date","special_project_code","finality_code","external_product_code","payment","interest","plan"]}},"required":["rq_header","rq_body"],"$schema":"http://json-schema.org/draft-04/schema#"}}],"responses":{"200":{"description":""}},"security":[]}}}}